pandamodelsbackend/__init__.py
pandamodelsbackend/pandaModelsBackend.py
pandamodelsbackend/tests/test_backend_api.py
pandamodelsbackend/tests/test_basic_usage.py
pandamodelsbackend-0.2.0.dist-info/licenses/LICENSE
pandamodelsbackend-0.2.0.dist-info/METADATA
pandamodelsbackend-0.2.0.dist-info/WHEEL
pandamodelsbackend-0.2.0.dist-info/top_level.txt
pandamodelsbackend-0.2.0.dist-info/RECORD
