Metadata-Version: 2.4
Name: pandamodelsbackend
Version: 0.2.0
Summary: A PowerModels Backend for Grid2op using PandaModels through PandaPower
Author-email: Ketan Bhardwaj <ketanbj@gmail.com>
License: MIT License
Project-URL: repository, https://github.com/MOSSLab-MIT/PandaModelsBackend
Project-URL: changelog, https://github.com/MOSSLab-MIT/PandaModelsBackend/blob/main/changelog.md
Project-URL: issues, https://github.com/MOSSLab-MIT/PandaModelsBackend/issues
Classifier: Development Status :: 4 - Beta
Classifier: Intended Audience :: Science/Research
Classifier: Programming Language :: Python :: 3 :: Only
Classifier: Programming Language :: Python :: 3
Classifier: Programming Language :: Python :: 3.12
Classifier: Programming Language :: Python :: 3.13
Requires-Python: >=3.12
License-File: LICENSE
Requires-Dist: numpy<2.0
Requires-Dist: scipy
Requires-Dist: pandas
Requires-Dist: pandapower<3.0
Requires-Dist: grid2op<1.11
Provides-Extra: tests
Requires-Dist: setuptools; extra == "tests"
Provides-Extra: numba
Requires-Dist: numba; extra == "numba"
Dynamic: license-file
